bci_framework/__init__.py
bci_framework/__main__.py
bci_framework/_version.txt
bci_framework/custom.css
bci_framework/assets/banner.png
bci_framework/assets/banner.svg
bci_framework/assets/bciframework.default
bci_framework/assets/jupyter.template.ipynb
bci_framework/assets/.ipynb_checkpoints/jupyter-checkpoint.ipynb
bci_framework/assets/.ipynb_checkpoints/jupyter.template-checkpoint.ipynb
bci_framework/assets/fonts/dejavu/AUTHORS
bci_framework/assets/fonts/dejavu/BUGS
bci_framework/assets/fonts/dejavu/LICENSE
bci_framework/assets/fonts/dejavu/NEWS
bci_framework/assets/fonts/dejavu/README.md
bci_framework/assets/fonts/dejavu/langcover.txt
bci_framework/assets/fonts/dejavu/status.txt
bci_framework/assets/fonts/dejavu/unicover.txt
bci_framework/assets/fonts/dejavu/fontconfig/20-unhint-small-dejavu-sans-mono.conf
bci_framework/assets/fonts/dejavu/fontconfig/20-unhint-small-dejavu-sans.conf
bci_framework/assets/fonts/dejavu/fontconfig/20-unhint-small-dejavu-serif.conf
bci_framework/assets/fonts/dejavu/fontconfig/57-dejavu-sans-mono.conf
bci_framework/assets/fonts/dejavu/fontconfig/57-dejavu-sans.conf
bci_framework/assets/fonts/dejavu/fontconfig/57-dejavu-serif.conf
bci_framework/assets/fonts/dejavu/ttf/DejaVuMathTeXGyre.ttf
bci_framework/assets/fonts/dejavu/ttf/DejaVuSans-Bold.ttf
bci_framework/assets/fonts/dejavu/ttf/DejaVuSans-BoldOblique.ttf
bci_framework/assets/fonts/dejavu/ttf/DejaVuSans-ExtraLight.ttf
bci_framework/assets/fonts/dejavu/ttf/DejaVuSans-Oblique.ttf
bci_framework/assets/fonts/dejavu/ttf/DejaVuSans.ttf
bci_framework/assets/fonts/dejavu/ttf/DejaVuSansCondensed-Bold.ttf
bci_framework/assets/fonts/dejavu/ttf/DejaVuSansCondensed-BoldOblique.ttf
bci_framework/assets/fonts/dejavu/ttf/DejaVuSansCondensed-Oblique.ttf
bci_framework/assets/fonts/dejavu/ttf/DejaVuSansCondensed.ttf
bci_framework/assets/fonts/dejavu/ttf/DejaVuSansMono-Bold.ttf
bci_framework/assets/fonts/dejavu/ttf/DejaVuSansMono-BoldOblique.ttf
bci_framework-1.3.2.dist-info/LICENSE
bci_framework-1.3.2.dist-info/METADATA
bci_framework-1.3.2.dist-info/WHEEL
bci_framework-1.3.2.dist-info/entry_points.txt
bci_framework-1.3.2.dist-info/top_level.txt
bci_framework-1.3.2.dist-info/RECORD
