Metadata-Version: 2.1
Name: bci-framework
Version: 1.3.2
Summary: A real-time tool for acquisition, analysis and stimuli delivery for OpenBCI.
Download-URL: https://github.com/UN-GCPDS/bci_framework
Author: Yeison Cardona
Author-email: yencardonaal@unal.edu.co
Maintainer: Yeison Cardona
Maintainer-email: yencardonaal@unal.edu.co
License: BSD-2-Clause
Classifier: Development Status :: 4 - Beta
Classifier: Intended Audience :: Developers
Classifier: Intended Audience :: Education
Classifier: Intended Audience :: Healthcare Industry
Classifier: Intended Audience :: Science/Research
Classifier: License :: OSI Approved :: BSD License
Classifier: Programming Language :: Python :: 3.8
Classifier: Topic :: Scientific/Engineering
Classifier: Topic :: Scientific/Engineering :: Artificial Intelligence
Classifier: Topic :: Scientific/Engineering :: Human Machine Interfaces
Classifier: Topic :: Scientific/Engineering :: Medical Science Apps.
Classifier: Topic :: Software Development :: Embedded Systems
Classifier: Topic :: Software Development :: Libraries
Classifier: Topic :: Software Development :: Libraries :: Application Frameworks
Classifier: Topic :: Software Development :: Libraries :: Python Modules
Classifier: Topic :: System :: Hardware :: Hardware Drivers
Requires-Python: >=3.8
License-File: LICENSE
Requires-Dist: cycler
Requires-Dist: matplotlib
Requires-Dist: kafka-python
Requires-Dist: tornado
Requires-Dist: scipy
Requires-Dist: qt-material
Requires-Dist: numpy
Requires-Dist: mne
Requires-Dist: psutil
Requires-Dist: simple-pid
Requires-Dist: figurestream
Requires-Dist: gcpds
Requires-Dist: openbci-stream
Requires-Dist: PySide6
Requires-Dist: radiant
Requires-Dist: seaborn
